t.py
test.py
KeyisBClient/Clients.py
KeyisBClient/Exceptions.py
KeyisBClient/__init__.py
KeyisBClient/core.py
KeyisBClient/dnsCore.py
KeyisBClient/models.py
KeyisBClient/gn/__init__.py
KeyisBClient/gn/_func.py
KeyisBClient/gn/models.py
KeyisBClient/gw_certs/__init__.py
KeyisBClient/gw_certs/v0.0.1.crt
keyisbclient-1.4.0.1.75.dist-info/licenses/LICENSE
keyisbclient-1.4.0.1.75.dist-info/METADATA
keyisbclient-1.4.0.1.75.dist-info/WHEEL
keyisbclient-1.4.0.1.75.dist-info/top_level.txt
keyisbclient-1.4.0.1.75.dist-info/RECORD
