Metadata-Version: 2.4
Name: KeyisBClient
Version: 1.4.0.1.75
Summary: KeyisBClient
Home-page: https://github.com/KeyisB/libs/tree/main/KeyisBClient
Author: KeyisB
Author-email: keyisb.pip@gmail.com
License: MMB License v1.0
Classifier: Programming Language :: Python :: 3
Classifier: Operating System :: OS Independent
Requires-Python: >=3.12
License-File: LICENSE
Requires-Dist: KeyisBLogging
Requires-Dist: httpx
Requires-Dist: KeyisBClient-httpx
Requires-Dist: KeyisBClient-mmbp
Requires-Dist: msgpack
Dynamic: author
Dynamic: author-email
Dynamic: classifier
Dynamic: description
Dynamic: description-content-type
Dynamic: home-page
Dynamic: license
Dynamic: license-file
Dynamic: requires-dist
Dynamic: requires-python
Dynamic: summary
